{"cells":[{"name":{"_data_":"UWPD","_wellknowntype_":"string"},"views":[{"name":{"_data_":"layout","_wellknowntype_":"string"},"references":{"cells":[],"externalFiles":[],"libraries":[],"libraryFiles":[],"pcbVias":[],"views":[{"_data_":"ads_rflib:R:layout","_wellknowntype_":"string"},{"_data_":"ads_tlines:MCURVE:layout","_wellknowntype_":"string"},{"_data_":"ads_tlines:MLIN:layout","_wellknowntype_":"string"}]},"timestamp":[{"file":{"_data_":".","_wellknowntype_":"string"},"time":{"_data_":1701713685535,"_wellknowntype_":"int64"}},{"file":{"_data_":"layout.oa","_wellknowntype_":"string"},"time":{"_data_":1701713685530,"_wellknowntype_":"int64"}},{"file":{"_data_":"master.tag","_wellknowntype_":"string"},"time":{"_data_":1701386138669,"_wellknowntype_":"int64"}}]},{"name":{"_data_":"schematic","_wellknowntype_":"string"},"references":{"cells":[],"externalFiles":[],"libraries":[],"libraryFiles":[],"pcbVias":[],"views":[{"_data_":"ads_datacmps:VAR:symbol","_wellknowntype_":"string"},{"_data_":"ads_rflib:GROUND:symbol","_wellknowntype_":"string"},{"_data_":"ads_rflib:R:symbol","_wellknowntype_":"string"},{"_data_":"ads_simulation:S_Param:symbol","_wellknowntype_":"string"},{"_data_":"ads_simulation:Term:symbol","_wellknowntype_":"string"},{"_data_":"ads_tlines:MCURVE:symbol","_wellknowntype_":"string"},{"_data_":"ads_tlines:MLIN:symbol","_wellknowntype_":"string"},{"_data_":"ads_tlines:MSUB:symbol","_wellknowntype_":"string"}]},"timestamp":[{"file":{"_data_":".","_wellknowntype_":"string"},"time":{"_data_":1701844929698,"_wellknowntype_":"int64"}},{"file":{"_data_":"master.tag","_wellknowntype_":"string"},"time":{"_data_":1701386138759,"_wellknowntype_":"int64"}},{"file":{"_data_":"sch.oa","_wellknowntype_":"string"},"time":{"_data_":1701713742426,"_wellknowntype_":"int64"}}]},{"name":{"_data_":"symbol","_wellknowntype_":"string"},"references":{"cells":[],"externalFiles":[],"libraries":[],"libraryFiles":[],"pcbVias":[],"views":[]},"timestamp":[{"file":{"_data_":".","_wellknowntype_":"string"},"time":{"_data_":1701386138853,"_wellknowntype_":"int64"}},{"file":{"_data_":"master.tag","_wellknowntype_":"string"},"time":{"_data_":1701386138797,"_wellknowntype_":"int64"}},{"file":{"_data_":"named.views","_wellknowntype_":"string"},"time":{"_data_":1701385387792,"_wellknowntype_":"int64"}},{"file":{"_data_":"symbol.oa","_wellknowntype_":"string"},"time":{"_data_":1701386138804,"_wellknowntype_":"int64"}}]}]},{"name":{"_data_":"cell_1","_wellknowntype_":"string"},"views":[{"name":{"_data_":"layout","_wellknowntype_":"string"},"references":{"cells":[],"externalFiles":[],"libraries":[],"libraryFiles":[],"pcbVias":[],"views":[{"_data_":"ads_rflib:R:layout","_wellknowntype_":"string"},{"_data_":"ads_tlines:TLIN:layout","_wellknowntype_":"string"}]},"timestamp":[{"file":{"_data_":".","_wellknowntype_":"string"},"time":{"_data_":1701326683464,"_wellknowntype_":"int64"}},{"file":{"_data_":"layout.oa","_wellknowntype_":"string"},"time":{"_data_":1701326683461,"_wellknowntype_":"int64"}},{"file":{"_data_":"master.tag","_wellknowntype_":"string"},"time":{"_data_":1701326667673,"_wellknowntype_":"int64"}}]},{"name":{"_data_":"schematic","_wellknowntype_":"string"},"references":{"cells":[],"externalFiles":[],"libraries":[],"libraryFiles":[],"pcbVias":[],"views":[{"_data_":"ads_datacmps:VAR:symbol","_wellknowntype_":"string"},{"_data_":"ads_rflib:GROUND:symbol","_wellknowntype_":"string"},{"_data_":"ads_rflib:R:symbol","_wellknowntype_":"string"},{"_data_":"ads_simulation:S_Param:symbol","_wellknowntype_":"string"},{"_data_":"ads_simulation:Term:symbol","_wellknowntype_":"string"},{"_data_":"ads_tlines:TLIN:symbol","_wellknowntype_":"string"}]},"timestamp":[{"file":{"_data_":".","_wellknowntype_":"string"},"time":{"_data_":1701326722636,"_wellknowntype_":"int64"}},{"file":{"_data_":"master.tag","_wellknowntype_":"string"},"time":{"_data_":1701320420763,"_wellknowntype_":"int64"}},{"file":{"_data_":"sch.oa","_wellknowntype_":"string"},"time":{"_data_":1701326718701,"_wellknowntype_":"int64"}}]}]},{"name":{"_data_":"cosimulate","_wellknowntype_":"string"},"views":[]}],"name":{"_data_":"MyLibrary_lib","_wellknowntype_":"string"},"version":{"_data_":1.0,"_wellknowntype_":"double"}}